{
  "streams": [
    {
      "title": "sd",
      "description": "ew",
      "id": 1
    },
    {
      "title": "sd",
      "description": "ew",
      "id": 2
    },
    {
      "title": "cs",
      "description": "adsa",
      "id": 3
    },
    {
      "title": "cs",
      "description": "adsa",
      "id": 4
    },
    {
      "title": "cs",
      "description": "adsa",
      "id": 5
    },
    {
      "title": "ea",
      "description": "we",
      "id": 6
    },
    {
      "title": "dsji",
      "description": "ewd",
      "id": 7
    },
    {
      "title": "dsji",
      "description": "ewd",
      "id": 8
    },
    {
      "title": "Other Stream",
      "description": "Here's some stream",
      "id": 9
    },
    {
      "title": "Other Stream",
      "description": "Here's some stream",
      "id": 10
    },
    {
      "title": "ds",
      "description": "ds",
      "id": 11
    },
    {
      "title": "dsdas",
      "description": "dsa",
      "id": 12
    },
    {
      "title": "Arjit is",
      "description": "a good mzx",
      "id": 14
    },
    {
      "title": "ANSJn",
      "description": "asjdsjijds",
      "id": 15
    },
    {
      "title": "Streamy",
      "description": "It is a good platform",
      "userId": "100626309264880683286",
      "id": 16
    }
  ]
}